sansan.py
sansan-1.0.0.dist-info/WHEEL
sansan-1.0.0.dist-info/METADATA
sansan-1.0.0.dist-info/RECORD
