Metadata-Version: 2.1
Name: sansan
Version: 1.0.0
Summary: a = San() print(a.san1(123))
Author: Fazilbek
Requires-Python: >=3.9,<4.0
Classifier: Programming Language :: Python :: 3
Classifier: Programming Language :: Python :: 3.9
